git_multi_status/__init__.py
git_multi_status/__main__.py
git_multi_status/config.py
git_multi_status/display.py
git_multi_status/git_utils.py
git_multi_status/repo_finder.py
git_multi_status/status_checker.py
git_multi_status-0.1.0.dist-info/METADATA
git_multi_status-0.1.0.dist-info/WHEEL
git_multi_status-0.1.0.dist-info/entry_points.txt
git_multi_status-0.1.0.dist-info/RECORD
