Metadata-Version: 2.4
Name: git-multi-status
Version: 0.1.0
Summary: Python port of multi-git-status
Requires-Python: >=3.10
Requires-Dist: rich>=14.0.0
Requires-Dist: typer>=0.15.2
